llama_index/prompts/lmformatenforcer/__init__.py
llama_index/prompts/lmformatenforcer/utils.py
flying_delta_prompts_lmformatenforcer-0.1.0.dist-info/METADATA
flying_delta_prompts_lmformatenforcer-0.1.0.dist-info/WHEEL
flying_delta_prompts_lmformatenforcer-0.1.0.dist-info/RECORD
